pyrefdev/__init__.py
pyrefdev/__main__.py
pyrefdev/_version.py
pyrefdev/config.py
pyrefdev/server.py
pyrefdev/indexer/__main__.py
pyrefdev/indexer/add_docs.py
pyrefdev/indexer/crawl_docs.py
pyrefdev/indexer/crawl_pypi.py
pyrefdev/indexer/index.py
pyrefdev/indexer/parse_docs.py
pyrefdev/indexer/parse_pypi.py
pyrefdev/indexer/update_config.py
pyrefdev/indexer/update_docs.py
pyrefdev/indexer/update_landing_page.py
pyrefdev/mapping/__init__.py
pyrefdev/mapping/adtk.py
pyrefdev/mapping/aes-pkcs5.py
pyrefdev/mapping/aiodocker.py
pyrefdev/mapping/aiogoogle.py
pyrefdev/mapping/aiohttp.py
pyrefdev/mapping/aioice.py
pyrefdev/mapping/aioitertools.py
pyrefdev/mapping/aiokafka.py
pyrefdev/mapping/aiolimiter.py
pyrefdev/mapping/aiomysql.py
pyrefdev/mapping/aiopg.py
pyrefdev/mapping/aioquic.py
pyrefdev/mapping/aiortc.py
pyrefdev/mapping/aiosignal.py
pyrefdev/mapping/aiosmtplib.py
pyrefdev/mapping/aiostream.py
pyrefdev/mapping/aiounittest.py
pyrefdev/mapping/alabaster.py
pyrefdev/mapping/aleph-alpha-client.py
pyrefdev/mapping/alexapy.py
pyrefdev/mapping/altgraph.py
pyrefdev/mapping/androguard.py
pyrefdev/mapping/anyio.py
pyrefdev/mapping/anytree.py
pyrefdev/mapping/apache-beam.py
pyrefdev/mapping/apeye.py
pyrefdev/mapping/archspec.py
pyrefdev/mapping/arrow.py
pyrefdev/mapping/asammdf.py
pyrefdev/mapping/asn1.py
pyrefdev/mapping/astor.py
pyrefdev/mapping/asttokens.py
pyrefdev/mapping/asyncssh.py
pyrefdev/mapping/asyncstdlib.py
pyrefdev/mapping/asyncvnc.py
pyrefdev/mapping/attrs-strict.py
pyrefdev/mapping/attrs.py
pyrefdev/mapping/audit-alembic.py
pyrefdev/mapping/autobahn.py
pyrefdev/mapping/autodocsumm.py
pyrefdev/mapping/autoray.py
pyrefdev/mapping/autosemver.py
pyrefdev/mapping/azure-identity.py
pyrefdev/mapping/backoff-utils.py
pyrefdev/mapping/behave.py
pyrefdev/mapping/bezier.py
pyrefdev/mapping/bidict.py
pyrefdev/mapping/binaryornot.py
pyrefdev/mapping/bitstruct.py
pyrefdev/mapping/bleach.py
pyrefdev/mapping/bleak.py
pyrefdev/mapping/blessed.py
pyrefdev/mapping/blessings.py
pyrefdev-2025.11.dist-info/METADATA
pyrefdev-2025.11.dist-info/WHEEL
pyrefdev-2025.11.dist-info/entry_points.txt
pyrefdev-2025.11.dist-info/licenses/LICENSE
pyrefdev-2025.11.dist-info/RECORD
