Metadata-Version: 2.4
Name: pyrefdev
Version: 2025.11
Summary: The entry point to Python reference docs
Project-URL: Homepage, https://pyref.dev
Project-URL: Source, https://github.com/mangoumbrella/pyref.dev
Project-URL: Changelog, https://github.com/mangoumbrella/pyref.dev/blob/main/CHANGELOG.md
Author-email: Mango Umbrella LLC <hi@mangoumbrella.com>
License-Expression: Apache-2.0
License-File: LICENSE
Keywords: documentation
Classifier: Development Status :: 4 - Beta
Classifier: Environment :: Console
Classifier: Intended Audience :: Developers
Classifier: Operating System :: OS Independent
Classifier: Programming Language :: Python
Classifier: Programming Language :: Python :: 3 :: Only
Classifier: Programming Language :: Python :: 3.10
Classifier: Programming Language :: Python :: 3.11
Classifier: Programming Language :: Python :: 3.12
Classifier: Programming Language :: Python :: 3.13
Classifier: Programming Language :: Python :: 3.14
Classifier: Programming Language :: Python :: Free Threading
Classifier: Topic :: Documentation
Requires-Python: >=3.10
Requires-Dist: cyclopts>=3.19.0
Requires-Dist: jinja2>=3.1.6
Requires-Dist: packaging>=25.0
Requires-Dist: yib>=0.3.0
Provides-Extra: indexer
Requires-Dist: beautifulsoup4>=4.13.4; extra == 'indexer'
Requires-Dist: rich>=14.0.0; extra == 'indexer'
Provides-Extra: server
Requires-Dist: fastapi<1,>=0.115.12; extra == 'server'
Requires-Dist: uvicorn[standard]<1,>=0.34.2; extra == 'server'
